{
    "id": "7120bec8-8c73-4d78-93b1-61e29d32642f",
    "name": "This is a random type3 object xyPYcJKAfzVIKMObyPIHzfQxYxByGasfxXOOqUBQJrOGQYWUnHRsnJTmwHnwrcYLBfXpmpYSZltxKSZgMMV",
    "description": "Description kcekgBUqrkffRCPOKPWVSuNMypnmCMkXIjqXBeAZMsZBvQgfMPNrFserbgpDYagmGenWYKLNcBerehNKDpDlSxhVvWWARgsYYgHiDQPzCRPSc",
    "details": {
        "items": [
            "fiOmuVg",
            "rKVXewV",
            "WCjLEjEwHKBG",
            "hoMoILbX",
            "cldWXzuVrVgEpAAH",
            "ZEZWjacoYC",
            "wIMVR",
            "AhHKUPGzMUS",
            "MkVCHTLXYKhLzclyfY",
            "QIgALCiXKYc"
        ],
        "foo": [
            "yOWWfXcdOagzHnmwqlntphRoxZse",
            "shuJGXHXexeXJLCqdasPosMVShBUsj",
            "mOpbdGefPNZYWqUMmAWhCbc",
            "mvtNXnXCHaSZZzCIaUHSNtFjZoOZhFcSrkDO",
            "oeiBFykxHZmdhSqnICswstSMp",
            "ZDXwDAqPcCcnNXcMCFacuwJvgPwuaGv",
            "nblTOSyFAdLYZfJmAWFcT",
            "JkTjhIpeIWBRKHEwcDSRlmkb",
            "CSMLpltniFfOMjfFoKokFfFgFcEB",
            "pUZChjRxanRmiXumxmolkyeoaR",
            "MXwfpEfmqRWRzmKQMDGxdMP",
            "ERlTeGJxzcXVKlwyIeVzcibNz",
            "RrdaTmubKCussOiTXDdRDleWHfgTKVorqwC",
            "ZNAOPahOhmVBIVJzwiFdlbFaRDuhqmKgCCLJwM",
            "meIWOAAsLMuocxcteaRPUTUCAKyhzk",
            "PbhagsYygLueFMMXylJvYqqSVHIY",
            "AFJINpoJvaTJCjDVzinv",
            "wkyfKVOAyLuQfHsFHoscADUSnmmMzEUFKWEjglV",
            "iBAUvboSaePGAoUitzQjZRAQpreuxmNT",
            "BNraqUOcoOHoUeSRERAFIMaRfMwQNdDXgV",
            "JHyGFjEjTAYwNLshhVtQIaBjBoICCU",
            "nDfWvheOIOKNniyIgXWccfWUlkUVtJx",
            "VTfFCVBZGuadAvLjnBGflD",
            "JVahXSezmAXjknkpcrWJoQDshXF",
            "XaldfFaMPjOMsopBPnCfOmUPHGGOxh",
            "PLrZnIlkOsWIiFCWmCvQiozHJEXt",
            "hfQyPGbwhJiTkPVoRGbQRnEuAvZlWEvNxkrBQw",
            "SyDaHXXsALlclhCAqYeCkRsw",
            "gsEMxCATjMKdaDtPNgLr",
            "ngjsUGhWcoTHVUUaxXJCIOKqeheiqpJUNYqC",
            "GVMELJAjwAIwIaBDBXBOwauVHM",
            "rMSOUtByBZYpknvTDGKtltJ",
            "vSuxVybQEnNDppdlrCYFoSQBPlF",
            "UHFfvulRNmpanENGkYzUbHZnOeWYKRBmt",
            "BUVRfexTZsHigEnGsGnUaXdK",
            "ytGBdsjHbqydIsJhsmtcpcne",
            "IvYjcHmUqbKYZYEraOjfHxG",
            "iLzgCJByAsbgxQZIGqAFodfnVJKoEXYZdrljXw",
            "kCSxYdtOemSWDevzUmwGggYuLoa",
            "bpnviiRdWcDwZICNWquRwFUushHrChrn",
            "xUxjkYtXKkBNzsexMhuqcDraROcXwh",
            "BArrwpupjZwPZLaZkguFG",
            "QOpENJUvntsxeTvoXRXgZtUSUEvJRHTD",
            "OwqpETKZVpqSajHqeRAcnRVtyyVIna",
            "sJLQmkPpeYiSzxvduDsvDkNuvPPUxIWXNL",
            "DSjRkQwSVlBtGUDTceTrQIGgx",
            "fKPFZwOEavbmLJQCBlzLiG",
            "aWGsNYNHKwqXlveZHQkmqYwnoBgqoP",
            "RZszTaOeZXudptEVVeVDcFqFHcuXqQ",
            "MVrGUiDbGbriqzeVIluGxesd",
            "gLdZoAERUKmejegXnkBuDzq",
            "lveCchmWLaYAhWuUbVcQWQOy",
            "hoskXyckLGclsUieAPoItZQoQuwNND",
            "sAmdFMIAhMzmghMlVGXjFNQGrUba",
            "zoNuNPgAUwnSkBVPNoYCMxZISRDXUw",
            "iNZChAeFJFyHzJeeRSnmbfUQHmWLEJZAWAV",
            "ZfASmpfBuxtYydPSRozhCKKnOVHokTOOvb"
        ],
        "bar": [
            "OTbnrNOIUEfhKlQugHEdZHthZQIrrJ",
            "goeLVTESxmTpOIToiTmoE",
            "iLoeowoFpDHnZJhNfxKAuovxb",
            "awNvLgwqMWUGCOycfRbpJjhsYN",
            "BFIGtggItoWIIGVBdpereGszFV"
        ]
    }
}